textual_web/.DS_Store
textual_web/__init__.py
textual_web/_two_way_dict.py
textual_web/app_session.py
textual_web/apps/merlin.py
textual_web/apps/signup.py
textual_web/apps/signup.tcss
textual_web/apps/welcome.py
textual_web/cli.py
textual_web/config.py
textual_web/constants.py
textual_web/environment.py
textual_web/exit_poller.py
textual_web/ganglion_client.py
textual_web/identity.py
textual_web/packets.py
textual_web/poller.py
textual_web/retry.py
textual_web/session.py
textual_web/session_manager.py
textual_web/slugify.py
textual_web/terminal_session.py
textual_web/types.py
textual_web/web.py
textual_web-0.7.0.dist-info/LICENSE
textual_web-0.7.0.dist-info/METADATA
textual_web-0.7.0.dist-info/WHEEL
textual_web-0.7.0.dist-info/entry_points.txt
textual_web-0.7.0.dist-info/RECORD
