Metadata-Version: 2.1
Name: textual_web
Version: 0.7.0
Summary: Serve Textual apps
License: MIT
Author: Will McGugan
Author-email: will@textualize.io
Requires-Python: >=3.8,<4.0
Classifier: License :: OSI Approved :: MIT License
Classifier: Programming Language :: Python :: 3
Classifier: Programming Language :: Python :: 3.8
Classifier: Programming Language :: Python :: 3.9
Classifier: Programming Language :: Python :: 3.10
Classifier: Programming Language :: Python :: 3.11
Requires-Dist: aiohttp (>=3.9.3,<4.0.0)
Requires-Dist: aiohttp-jinja2 (>=1.5.1,<2.0.0)
Requires-Dist: click (>=8.1.3,<9.0.0)
Requires-Dist: httpx (>=0.24.1)
Requires-Dist: importlib-metadata (>=4.11.3)
Requires-Dist: msgpack (>=1.0.5,<2.0.0)
Requires-Dist: pydantic (>=2.1.1,<3.0.0)
Requires-Dist: textual (>=0.43.0,<0.44.0)
Requires-Dist: tomli (>=2.0.1,<3.0.0)
Requires-Dist: uvloop (>=0.19.0,<0.20.0) ; sys_platform != "win32"
Requires-Dist: xdg (>=6.0.0,<7.0.0)
